setup.py
ocsim/__init__.py
ocsim.egg-info/PKG-INFO
ocsim.egg-info/SOURCES.txt
ocsim.egg-info/dependency_links.txt
ocsim.egg-info/requires.txt
ocsim.egg-info/top_level.txt
ocsim/channel/EDFA.py
ocsim/channel/ROADM.py
ocsim/channel/__init__.py
ocsim/channel/fiber.py
ocsim/channel/impairments.py
ocsim/core/Signal.py
ocsim/core/__init__.py
ocsim/core/constl.py
ocsim/device_manager/__init__.py
ocsim/device_manager/device.py
ocsim/filter/__init__.py
ocsim/filter/filtering.py
ocsim/tranceiver/__init__.py
ocsim/tranceiver/dsp.py
ocsim/tranceiver/instruments.py
ocsim/tranceiver/numba_backend.py
ocsim/tranceiver/utilities.py
ocsim/under_test/__init__.py
ocsim/under_test/some_functions.py
ocsim/utilities/__init__.py
ocsim/utilities/utilities.py
ocsim/utilities/visulaization.py