Metadata-Version: 1.0
Name: ocsim
Version: 0.0.92
Summary: simulator for optical communications
Home-page: https://github.com/huazhixixi/ocsim.git
Author: huazhi lun
Author-email: huazhi.lun@sjtu.edu.cn
License: UNKNOWN
Platform: UNKNOWN
